django_simple_audit_gizmag-0.2.2.dist-info/DESCRIPTION.rst
django_simple_audit_gizmag-0.2.2.dist-info/METADATA
django_simple_audit_gizmag-0.2.2.dist-info/RECORD
django_simple_audit_gizmag-0.2.2.dist-info/WHEEL
django_simple_audit_gizmag-0.2.2.dist-info/metadata.json
django_simple_audit_gizmag-0.2.2.dist-info/top_level.txt
simple_audit/__init__.py
simple_audit/admin.py
simple_audit/apps.py
simple_audit/m2m_audit.py
simple_audit/managers.py
simple_audit/middleware.py
simple_audit/models.py
simple_audit/settings.py
simple_audit/signal.py
simple_audit/tests.py
simple_audit/views.py
simple_audit/locale/pt_BR/LC_MESSAGES/django.po
simple_audit/migrations/0001_initial.py
simple_audit/migrations/0002_auto_20160419_0448.py
simple_audit/migrations/__init__.py
simple_audit/templates/admin/simple_audit/audit/change_form.html
simple_audit/templatetags/__init__.py
simple_audit/templatetags/audit.py
